{
   "t":"ADC Readings",
   "g":[
      {
         "t":"MCU Status",
         "d":[
            {
               "t":"Runtime",
               "v":"%1",
               "u":"ms"
            }
         ]
      },
      {
         "t":"ADC Readings",
         "d":[
            {
               "t":"原始温度",
               "v":"%2",
               "g":true,
               "w":"bar",
               "min":0,
               "max":4096
            },
            {
               "t":"滤波后",
               "v":"%3",
               "g":true,
               "w":"bar",
               "min":0,
               "max":4096
            },
            {
               "t":"目标值",
               "v":"%4",
               "g":true,
               "w":"bar",
               "min":0,
               "max":500
            },
            {
               "t":"当前温度值",
               "v":"%5",
               "g":true,
               "w":"bar",
               "min":0,
               "max":500
            },
            {
               "t":"占空比",
               "v":"%6",
               "g":true,
               "w":"bar",
               "min":0,
               "max":10000
            }
         ]
      }
   ]
}
